Workbook

Sheet README
A1: Merger & Financial Model — Microsoft / Activision Blizzard
A3: Purpose
A4: Sources & uses, purchase price allocation, pro forma income statement combination, and EPS accretion/dilution analysis for Microsoft's acquisition of Activision Blizzard.
A6: Tabs
A7: Assumptions | B7: Deal terms, financing mix, synergy phase-in, and rate assumptions
A8: Sources & Uses | B8: Financing sources and uses of funds at closing
A9: Purchase Price Allocation | B9: Goodwill and intangible asset allocation (ties to Microsoft's actual disclosed PPA)
A10: Pro Forma Combination | B10: Combined income statement with purchase-accounting adjustments
A11: Accretion-Dilution | B11: Standalone vs. pro forma EPS comparison
A13: Color Legend
A14: Blue text | B14: Hardcoded input — edit here
A15: Black text | B15: Formula — do not hardcode
A16: Green text | B16: Link to another sheet
A18: Sources
A19: Actual purchase price allocation, closing consideration, and FY2024 pro forma figures per Microsoft's FY2024 Form 10-K. Standalone FY2022 financials per Microsoft and Activision Blizzard Form 10-K filings. Financing mix and synergy phase-in are illustrative modeling assumptions.

Sheet Assumptions
A1: Deal Assumptions
A3: Transaction Terms
A4: Offer price per share ($) | B4: 95 | C4: Announced Jan. 18, 2022
A5: Fully diluted shares acquired, at closing (mn) | B5: 793.7684 | C5: Implied by $75.4bn total consideration ÷ $95.00 (10-K)
A6: Total purchase consideration ($mn) | B6: =B4*B5 -> 75407.998 | C6: Offer price × diluted shares at closing
A7: Activision Blizzard cash acquired ($mn) | B7: 12976 | C7: Per Microsoft FY2024 10-K purchase price allocation
A9: Financing Mix
A10: Cash on hand used ($mn) | B10: =B6+'Sources & Uses'!B10-B11 -> 48707.998 | C10: Plug: balances to total uses (purchase price + fees) less new borrowings
A11: New short-term borrowings ($mn) | B11: 27000 | C11: Commercial paper issued at closing, per public reporting
A12: Total sources | B12: =B10+B11 -> 75707.998
A13: Interest rate on new short-term borrowings | B13: 0.045
A14: Foregone interest rate on cash used | B14: 0.015
A16: Purchase Accounting & Synergies
A17: Acquired intangible assets ($mn) | B17: 21969 | C17: Per Microsoft FY2024 10-K PPA
A18: Blended amortization life (years) | B18: 15
A19: Pre-tax run-rate cost synergies ($mn) | B19: 300 | C19: Illustrative; Microsoft has not disclosed a formal synergy target
A20: % of synergies realized in Year 1 | B20: 0.4
A21: Marginal tax rate (for deal-related adjustments) | B21: 0.21
A22: Microsoft standalone effective tax rate (FY2022 actual) | B22: 0.1283 | C22: 1 − ($72,700mn net income ÷ $83,400mn operating income), per Microsoft FY2022 10-K

Sheet Sources & Uses
A1: Sources & Uses of Funds — At Closing (Oct. 13, 2023)
A3: Sources
A4: Cash on hand | B4: =Assumptions!B10 -> 48707.998
A5: New short-term borrowings | B5: =Assumptions!B11 -> 27000
A6: Total Sources | B6: =SUM(B4:B5) -> 75707.998
A8: Uses
A9: Purchase of Activision Blizzard equity | B9: =Assumptions!B4*Assumptions!B5 -> 75407.998
A10: Estimated transaction fees & expenses | B10: 300
A11: Total Uses | B11: =SUM(B8:B10) -> 75707.998
A13: Check: Sources − Uses (should equal zero) | B13: =B6-B11 -> 0

Sheet Purchase Price Allocation
A1: Purchase Price Allocation (Actual, per Microsoft FY2024 Form 10-K)
A3: Purchase Price Allocation ($ in millions)
A4: Cash and cash equivalents acquired | B4: 12976
A5: Goodwill | B5: 50969
A6: Intangible assets acquired | B6: 21969
A7: Other assets | B7: 2501
A8: Less: Long-term debt assumed | B8: -2799
A9: Less: Long-term income taxes | B9: -1914
A10: Less: Deferred income taxes | B10: -4677
A11: Less: Other liabilities | B11: -3617
A12: Total Purchase Price | B12: =SUM(B4:B11) -> 75408
A14: Check vs. Assumptions tab total consideration | B14: =B12-Assumptions!B6 -> 0.002
A17: Acquired Intangible Assets Detail
A18: Category | B18: Fair Value ($mn) | C18: Useful Life (yrs)
A19: Marketing-related (trademarks, franchise brands) | B19: 11619 | C19: 24
A20: Technology-based | B20: 9689 | C20: 4
A21: Customer-related | B21: 661 | C21: 4
A22: Total | B22: =SUM(B19:B21) -> 21969 | C22: =SUMPRODUCT(B19:B21,C19:C21)/B22 -> 14.577632

Sheet Pro Forma Combination
A1: Pro Forma Income Statement Combination (Illustrative, Full-Year Basis)
A3: ($ in millions) | B3: Microsoft Standalone | C3: Activision Blizzard Standalone | D3: Adjustments | E3: Pro Forma Combined
A4: Revenue | B4: 198270 | C4: 7530 | D4: =Assumptions!B19*0 -> 0 | E4: =SUM(B4:D4) -> 205800
A5: EBITDA | B5: 97860 | C5: 2450 | D5: =Assumptions!B19*Assumptions!B20 -> 120 | E5: =SUM(B5:D5) -> 100430
A6: Less: D&A (standalone) | B6: -14460 | C6: -360 | D6: =0 -> 0 | E6: =SUM(B6:D6) -> -14820
A7: Less: Incremental intangible amortization | B7: 0 | C7: 0 | D7: =-Assumptions!B17/Assumptions!B18 -> -1464.6 | E7: =SUM(B7:D7) -> -1464.6
A8: EBIT | B8: =B5+B6 -> 83400 | C8: =C5+C6 -> 2090 | D8: =D5+D6+D7 -> -1344.6 | E8: =SUM(B8:D8) -> 84145.4
A9: Less: Incremental interest on new debt | B9: 0 | C9: 0 | D9: =-Assumptions!B11*Assumptions!B13 -> -1215 | E9: =SUM(B9:D9) -> -1215
A10: Less: Foregone interest income on cash used | B10: 0 | C10: 0 | D10: =-Assumptions!B10*Assumptions!B14 -> -730.61997 | E10: =SUM(B10:D10) -> -730.61997
A11: Pre-tax income | B11: =B8+B9+B10 -> 83400 | C11: =C8+C9+C10 -> 2090 | D11: =D8+D9+D10 -> -3290.22 | E11: =SUM(B11:D11) -> 82199.78
A12: Less: Income taxes | B12: =-B11*Assumptions!B22 -> -10700.22 | C12: =-C11*Assumptions!B21 -> -438.9 | D12: =-D11*Assumptions!B21 -> 690.94619 | E12: =SUM(B12:D12) -> -10448.174
A13: Net Income | B13: =B11+B12 -> 72699.78 | C13: =C11+C12 -> 1651.1 | D13: =D11+D12 -> -2599.2738 | E13: =SUM(B13:D13) -> 71751.606

Sheet Accretion-Dilution
A1: EPS Accretion / (Dilution) Analysis
A3: Note: as an all-cash transaction, Microsoft's diluted share count is unchanged pro forma — 100% of the EPS impact flows through net income.
A5: Standalone vs. Pro Forma
B6: Microsoft Standalone | C6: Pro Forma Combined
A7: Net income ($mn) | B7: ='Pro Forma Combination'!B13 -> 72699.78 | C7: ='Pro Forma Combination'!E13 -> 71751.606
A8: Diluted shares outstanding (mn) | B8: 7534 | C8: =B8 -> 7534
A9: Diluted EPS ($) | B9: =B7/B8 -> 9.6495593 | C9: =C7/C8 -> 9.5237067
A11: EPS Accretion / (Dilution) — $ | B11: =C9-B9 -> -0.12585264
A12: EPS Accretion / (Dilution) — % | B12: =C9/B9-1 -> -0.01304232
A15: Interpretation
A16: This illustrative model reflects Year-1 run-rate dynamics (incremental intangible amortization, financing cost, and partial synergy realization). Microsoft's own FY2024 disclosure showed a near-neutral GAAP EPS impact through the first full fiscal year post-close (Section 9.4 of the report) — consistent with the purchase-accounting drag illustrated in this model moderating over time as amortization of shorter-lived intangibles burns off and synergies ramp toward the run-rate assumption above.
