Workbook

Sheet README
A1: Precedent Transaction Analysis — Activision Blizzard, Inc.
A3: Purpose
A4: Selected precedent M&A transactions in the interactive entertainment sector, used to benchmark the implied multiples paid by Microsoft for Activision Blizzard.
A6: Tabs
A7: Transactions | B7: Deal list with target financials at announcement and implied multiples (formula-linked)
A8: Summary | B8: Median/mean multiples and implied valuation range for ATVI
A10: Color Legend
A11: Blue text | B11: Hardcoded input — edit here
A12: Black text | B12: Formula — do not hardcode
A14: Sources
A15: Deal values are publicly disclosed headline figures. Target revenue/EBITDA at announcement are illustrative, approximate estimates for transactions where not separately disclosed by the parties; treat implied multiples for those deals as directional only.

Sheet Transactions
A1: Precedent Transaction Analysis
A3: Date | B3: Acquirer | C3: Target | D3: Deal Value ($mn) | E3: Target Revenue ($mn) | F3: Target EBITDA ($mn) | G3: EV / Revenue | H3: EV / EBITDA
A4: Sept. 2020 | B4: Microsoft | C4: ZeniMax Media (Bethesda Softworks) | D4: 7500 | E4: 1150 | F4: 340 | G4: =D4/E4 -> 6.5217391 | H4: =D4/F4 -> 22.058824
A5: Jan. 2022 | B5: Take-Two Interactive | C5: Zynga | D5: 12700 | E5: 2670 | F5: 400 | G5: =D5/E5 -> 4.7565543 | H5: =D5/F5 -> 31.75
A6: Jan. 2022 | B6: Sony Interactive Entertainment | C6: Bungie | D6: 3600 | E6: 260 | F6: 180 | G6: =D6/E6 -> 13.846154 | H6: =D6/F6 -> 20
A7: May 2022 | B7: Embracer Group | C7: Square Enix Western Studios | D7: 300 | E7: 300 | F7: 40 | G7: =D7/E7 -> 1 | H7: =D7/F7 -> 7.5
A8: 2023 | B8: Savvy Games Group (Saudi PIF) | C8: Scopely | D8: 4900 | E8: 1000 | F8: 220 | G8: =D8/E8 -> 4.9 | H8: =D8/F8 -> 22.272727
A9: Jan. 2022 | B9: Microsoft | C9: Activision Blizzard | D9: 68700 | E9: 8803 | F9: 3785 | G9: =D9/E9 -> 7.8041577 | H9: =D9/F9 -> 18.150594
A11: Median (excl. Microsoft/ATVI) | G11: =MEDIAN(G4:G8) -> 4.9 | H11: =MEDIAN(H4:H8) -> 22.058824
A12: Mean (excl. Microsoft/ATVI) | G12: =AVERAGE(G4:G8) -> 6.2048895 | H12: =AVERAGE(H4:H8) -> 20.71631

Sheet Summary
A1: Implied Valuation — Applying Precedent Transaction Multiples
A3: ATVI FY2021 Financials (Source: ATVI 10-K)
A4: Net revenue ($mn) | B4: 8803
A5: EBITDA ($mn) | B5: 3785
A6: Net cash ($mn) | B6: 6370
A7: Diluted shares outstanding (mn) | B7: 723
A9: Implied Value Per Share by Methodology
A10: Methodology | B10: Low Multiple | C10: High Multiple | D10: Implied EV Low | E10: Implied EV High | F10: Value / Share ($)
A11: EV / Revenue (precedent range) | B11: =MIN(Transactions!G11,Transactions!G12) -> 4.9 | C11: =MAX(Transactions!G11,Transactions!G12) -> 6.2048895 | D11: =MIN(B11:C11)*$B$4+$B$6 -> 49504.7 | E11: =MAX(B11:C11)*$B$4+$B$6 -> 60991.642 | F11: =AVERAGE(D11:E11)/$B$7 -> 76.415174
A12: EV / EBITDA (precedent range) | B12: =MIN(Transactions!H11,Transactions!H12) -> 20.71631 | C12: =MAX(Transactions!H11,Transactions!H12) -> 22.058824 | D12: =MIN(B12:C12)*$B$5+$B$6 -> 84781.234 | E12: =MAX(B12:C12)*$B$5+$B$6 -> 89862.647 | F12: =AVERAGE(D12:E12)/$B$7 -> 120.77723
A14: Microsoft offer price | F14: 95
A16: Actual implied multiples paid (Microsoft / ATVI)
A17: EV / Revenue paid | B17: =Transactions!G9 -> 7.8041577
A18: EV / EBITDA paid | B18: =Transactions!H9 -> 18.150594
